{
  "policySlug": "komei-kokumin",
  "policyLabel": "国民民主党・公明（超党派協力）",
  "excerpt": {
    "parties": "2026年6月の国会審議で、国民民主党・公明党が他党と共同提出・協力した争点（学校教育法附帯決議・国民投票法改正）に関与している2党を選定。",
    "politicians": "本案件の primarySpeech（古賀千景・五派共同附帯決議）と、国民民主・公明の個別発言を対比用に参照。"
  },
  "parties": [
    {
      "partyLabel": "国民民主党",
      "policyPledgeUrl": "",
      "policyPledgeSummary": "公約なし・発言ベース評価",
      "stance": {
        "text": "国民投票法のインターネット有料広告規制・広告ライブラリー法制化を今国会中に具体化すべき",
        "sourceUrl": "https://kokkai.ndl.go.jp/txt/122104183X00820260604/8",
        "sourceType": "国会発言（党所属議員）",
        "capturedAt": "2026-06-27"
      },
      "action": {
        "text": "2026-06-11、自民・維新・国民民主・参政党の共同提案として国民投票法三項目改正案を再提出（新藤義孝説明）",
        "speechUrl": "https://kokkai.ndl.go.jp/txt/122104183X00920260611/2",
        "capturedAt": "2026-06-27"
      },
      "symbol": "▲",
      "symbolReason": "公約なし・発言ベース評価。広告規制強化の方向で共同法案提出済み。成立に向けて進行中"
    },
    {
      "partyLabel": "公明党",
      "policyPledgeUrl": "",
      "policyPledgeSummary": "公約なし・発言ベース評価",
      "stance": {
        "text": "超党派で子どもの教育環境を築く必要性を表明。義務教育段階の給食無償化開始を評価",
        "sourceUrl": "https://kokkai.ndl.go.jp/txt/122115104X00920260609/5",
        "sourceType": "国会発言（党所属議員）",
        "capturedAt": "2026-06-27"
      },
      "action": {
        "text": "2026-06-09、自民・立憲・国民民主・公明・維新の五派共同附帯決議を学校教育法改正案に提出",
        "speechUrl": "https://kokkai.ndl.go.jp/txt/122115104X00920260609/73",
        "capturedAt": "2026-06-27"
      },
      "symbol": "▲",
      "symbolReason": "公約なし・発言ベース評価。超党派協力・附帯決議提出済み。法整備に向けて進行中"
    }
  ],
  "relatedArticleSlug": "komei-kokumin",
  "updatedAt": "2026-06-27T02:35:34.679Z",
  "methodologyVersion": "v1-manual",
  "disclaimer": "党の公式評価ではなく、公言と行動の整理表です。"
}