{
  "policySlug": "pension-kuriage-70",
  "policyLabel": "【年金繰下げ】70歳まで受取開始を遅らせると月額はいくら増える？",
  "relatedArticleSlug": "pension-kuriage-70",
  "updatedAt": "2026-07-08T17:30:03.891Z",
  "methodologyVersion": "v2-merits",
  "disclaimer": "報道・公表資料に基づく整理表です。党・団体の公式評価ではありません。",
  "excerpt": {
    "parties": "メリデメ・出典から自動構成（2立場）",
    "politicians": ""
  },
  "parties": [
    {
      "partyLabel": "推進・賛成側",
      "stance": {
        "text": "老齢年金の「繰下げ受給」は、開始年齢を65歳以降（最大75歳）まで遅らせると、月額が増える制度（日本年金機構）。",
        "sourceUrl": "https://www.nenkin.go.jp/service/kounen/kuriage/index.html",
        "sourceType": "報道",
        "capturedAt": "2026-06-27"
      },
      "action": {
        "text": "70歳まで繰下げた場合、増加率は公表表により最大約42%増（開始年齢・種類で異なる）。",
        "speechUrl": "https://www.nenkin.go.jp/service/kounen/kuriage/index.html",
        "capturedAt": "2026-06-27"
      },
      "symbol": "▲",
      "symbolReason": "推進側の公表・報道に基づく整理（進行中）"
    },
    {
      "partyLabel": "慎重・反対側",
      "stance": {
        "text": "老齢年金の「繰下げ受給」は、開始年齢を65歳以降（最大75歳）まで遅らせると、月額が増える制度（日本年金機構）。",
        "sourceUrl": "https://www.mhlw.go.jp/stf/seisakunitsuite/bunya/nenkin/nenkin/index.html",
        "sourceType": "報道",
        "capturedAt": "2026-06-27"
      },
      "action": {
        "text": "70歳まで繰下げた場合、増加率は公表表により最大約42%増（開始年齢・種類で異なる）。",
        "speechUrl": "https://www.mhlw.go.jp/stf/seisakunitsuite/bunya/nenkin/nenkin/index.html",
        "capturedAt": "2026-06-27"
      },
      "symbol": "×",
      "symbolReason": "反対・懸念の公表・試算に基づく整理"
    }
  ]
}
