{
  "slug": "bouka-taisaku",
  "title": "物価高対策 — あの話どうなった？",
  "tags": [
    "経済",
    "国会"
  ],
  "category": "国会",
  "searchKeyword": "物価",
  "fetchedAt": "2026-06-26T08:23:10.307Z",
  "apiHits": 1101,
  "nowSummary": {
    "label": "いまの結論（AI・平易語）",
    "bullets": [
      "物価高止まりが続く前提で、対策用の予備費1兆円を確保",
      "単なる高騰想定の予備ではなく、不足時の機動対応が目的",
      "2024年9月、燃料油価格対策などに使途を決定"
    ],
    "disclaimer": "AI補助による平易語要約です。解釈を含みます。数字・引用・発言内容の正本は primarySpeech.speechFull（国会議事録原文）をご確認ください。",
    "updatedAt": "2026-06-26T08:46:34.664Z"
  },
  "primarySpeech": {
    "speechID": "122104127X00220260603_032",
    "issueID": "122104127X00220260603",
    "date": "2026-06-03",
    "nameOfHouse": "衆議院",
    "nameOfMeeting": "決算行政監視委員会",
    "session": 221,
    "issue": "第2号",
    "speaker": "片山さつき",
    "speakerGroup": "自由民主党・無所属の会",
    "speakerPosition": "財務大臣・内閣府特命担当大臣（金融）",
    "speechURL": "https://kokkai.ndl.go.jp/txt/122104127X00220260603/32",
    "meetingURL": "https://kokkai.ndl.go.jp/txt/122104127X00220260603",
    "excerpt": "○片山国務大臣 令和六年度の一般会計予算の原油価格・物価高騰対策及び賃上げ促進環境整備対応予備費、当初一・〇兆円ですね。 物価が当初の想定よりも高騰した場合に備えて計上していたということよりは、物価の高止まりが国民生活に与える影響の先行きを正確に見通すことが困難であるような中で、物価と賃金の好循環に向け、賃上げ促進の環境整備を含め、物価高対策に必要となる経費に予期せぬ不足が生じた際には機動的に対応できるようにするために計上したというふうに承知しております。 そのために、当初の想定よりも物価が高騰したかどうかを理由としたというわけではなくて、…",
    "speechFull": "○片山国務大臣　令和六年度の一般会計予算の原油価格・物価高騰対策及び賃上げ促進環境整備対応予備費、当初一・〇兆円ですね。\r\n　物価が当初の想定よりも高騰した場合に備えて計上していたということよりは、物価の高止まりが国民生活に与える影響の先行きを正確に見通すことが困難であるような中で、物価と賃金の好循環に向け、賃上げ促進の環境整備を含め、物価高対策に必要となる経費に予期せぬ不足が生じた際には機動的に対応できるようにするために計上したというふうに承知しております。\r\n　そのために、当初の想定よりも物価が高騰したかどうかを理由としたというわけではなくて、物価水準が高止まる中で、厳しい状況が続く国民の皆様にきめ細かい支援を行うため、令和六年の九月に使用決定を行って、燃料油価格激変緩和対策事業等に必要な経費などに充てたというふうに承知をしております。"
  },
  "xPosts": [
    {
      "slot": 1,
      "status": "url_found",
      "post_url": "https://x.com/tamakiyuichiro/status/1719652949000159463",
      "account_label": "玉木雄一郎（国民民主党） (@tamakiyuichiro)",
      "speaker_hint": "片山さつき",
      "captured_at": null,
      "screenshot": null,
      "note": "X-researcher: web検索でURL登録（スクショは未取得）"
    },
    {
      "slot": 2,
      "status": "url_found",
      "post_url": "https://x.com/tamakiyuichiro/status/1567315242740502529",
      "account_label": "玉木雄一郎（国民民主党） (@tamakiyuichiro)",
      "speaker_hint": "片山さつき",
      "captured_at": null,
      "screenshot": null,
      "note": "X-researcher: web検索でURL登録（スクショは未取得）"
    },
    {
      "slot": 3,
      "status": "url_found",
      "post_url": "https://x.com/satsukikatayama/status/1901135682971836569",
      "account_label": "片山さつき (@satsukikatayama)",
      "speaker_hint": "片山さつき",
      "captured_at": null,
      "screenshot": null,
      "note": "X-researcher: web検索でURL登録（スクショは未取得）"
    },
    {
      "slot": 4,
      "status": "url_found",
      "post_url": "https://x.com/kirayoshiko/status/1037571806255665152",
      "account_label": "吉良よし子 (@kirayoshiko)",
      "speaker_hint": "片山さつき",
      "captured_at": null,
      "screenshot": null,
      "note": "X-researcher: web検索でURL登録（スクショは未取得）"
    },
    {
      "slot": 5,
      "status": "url_found",
      "post_url": "https://x.com/kondokazuya_/status/1763135258084741564",
      "account_label": "近藤和也 (@kondokazuya_)",
      "speaker_hint": "片山さつき",
      "captured_at": null,
      "screenshot": null,
      "note": "X-researcher: web検索でURL登録（スクショは未取得）"
    }
  ],
  "youtubeShorts": [],
  "legalReview": {
    "status": "ok",
    "agent": "legal-check",
    "ownerSignedAt": "2026-06-26",
    "note": "O8オーナー確認済。L5/L3修正済。agent再スキャン推奨"
  },
  "publishReady": true,
  "summaryBullets": [
    "対策費の不足が出たときに柔軟に充てられる枠。",
    "賃上げ促進の環境整備も対象に含む。",
    "燃料油価格激変緩和事業へ充当済み。",
    "2024年9月、関連経費などに使途を決定。"
  ],
  "plainExplanation": "衆議院の決算行政監視委員会（2026-06-03）で、片山さつき（自由民主党・無所属の会）が発言した内容を整理しています。 要点は「単なる高騰想定の予備ではなく、不足時の機動対応が目的 2024年9月、燃料油価格対策などに使途を決定」などです。\n\nここでの整理は発言の一部を平易に言い換えたもので、政府・与党・野党の公式見解を断定するものではありません。数字や引用の正本は原文リンクで確認できます。",
  "glossary": [
    {
      "term": "物価",
      "definition": "物やサービスの値段水準のこと"
    },
    {
      "term": "物価高騰",
      "definition": "物の値段が続けて上がること"
    },
    {
      "term": "賃上げ",
      "definition": "企業が従業員の給料や賃金を引き上げること"
    },
    {
      "term": "予備費",
      "definition": "予見しにくい支出に備えて、年度の予算に最初から計上しておく経費"
    }
  ],
  "stanceMatrix": {
    "policySlug": "bouka-taisaku",
    "dataPath": "data/policy-matrix/bouka-taisaku.json",
    "disclaimer": "党・個人の評価ではなく、出典付きの事実整理です。PoC手動データ。",
    "highlightPoliticians": [
      "katayama-satsuki",
      "tano-midori"
    ]
  },
  "xResearch": {
    "researched_at": "2026-06-26T09:23:17.357Z",
    "urls_found": 3,
    "method": "jina_reader+fxtwitter_public"
  }
}
