{
  "slug": "komei-kokumin",
  "title": "学校教育法改正とデジタル教科書",
  "tags": [
    "教育",
    "デジタル"
  ],
  "category": "教育",
  "searchKeyword": "学校教育法 デジタル教科書 改正",
  "fetchedAt": "2026-07-06T18:50:02.911Z",
  "apiHits": 4316,
  "sourceUrls": [
    "https://www.mext.go.jp/b_menu/activity/detail/2026/20260529_2.html",
    "https://www.mext.go.jp/b_menu/houan/an/detail/mext_03491.html",
    "https://www.kyobun.co.jp/article/2026061002"
  ],
  "nowSummary": {
    "label": "いまの結論",
    "bullets": [
      "正規のデジタル教科書や紙・デジタル併用型も、義務教育段階で無償給与の対象になる。",
      "附帯決議は、教科書分量やデジタル教材との役割分担を検討し、子どもと学校現場の負担軽減を図るよう求めている。",
      "語学の音声、実験手順の動画など、紙だけでは伝えにくい内容を正式な教科書の一部として扱いやすくなる。"
    ],
    "disclaimer": "AI補助による平易語要約です。解釈を含みます。数字・引用・発言内容の正本は primarySpeech.speechFull（国会議事録原文）をご確認ください。 国会議事録以外の案件です。正本は各出典リンクをご確認ください。",
    "updatedAt": "2026-07-07T01:48:27.977Z"
  },
  "primarySpeech": {
    "speechID": null,
    "issueID": null,
    "date": "2026-06-10",
    "nameOfHouse": "教育",
    "nameOfMeeting": "報道・公開情報",
    "session": 221,
    "issue": "第11号",
    "speaker": "松本大臣",
    "speakerGroup": "文部科学省",
    "speakerPosition": "文部科学大臣",
    "speechURL": "https://www.kyobun.co.jp/article/2026061002",
    "meetingURL": "https://www.kyobun.co.jp/article/2026061002",
    "speechFull": null
  },
  "xPosts": [],
  "youtubeShorts": [],
  "legalReview": {
    "status": "ok",
    "agent": "legal-check",
    "checkedAt": "2026-06-27T02:35:34.679Z",
    "note": "L1-L9 問題なし（batch4自動スキャン）"
  },
  "publishReady": true,
  "summaryBullets": [
    "2026-05-29：文部科学省は紙を一律廃止しないと説明しているが、どの教科・学年でどう使い分けるかは今後の指針と採択運用に左右される。",
    "2026-06-10：正規のデジタル教科書や紙・デジタル併用型も、義務教育段階で無償給与の対象になる。",
    "2026-06-10：附帯決議は、教科書分量やデジタル教材との役割分担を検討し、子どもと学校現場の負担軽減を図るよう求めている。"
  ],
  "plainExplanation": "学校教育法 デジタル教科書 改正について、公開されている報道・試算を時系列で整理しています。\n\n・正規のデジタル教科書や紙・デジタル併用型も、義務教育段階で無償給与の対象になる。\n・附帯決議は、教科書分量やデジタル教材との役割分担を検討し、子どもと学校現場の負担軽減を図るよう求めている。\n・語学の音声、実験手順の動画など、紙だけでは伝えにくい内容を正式な教科書の一部として扱いやすくなる。\n\nここでの要約は出典の見出し・リード文を平易に並べたものです。事実認定や有罪・無罪の判断はしていません。",
  "glossary": [
    {
      "term": "学校教育法",
      "definition": "この記事で追っているテーマの核心"
    },
    {
      "term": "公選法",
      "definition": "選挙の公正を守る法律。虚偽の経歴記載などが問題になることがある"
    }
  ],
  "xResearch": {
    "researched_at": "2026-07-06T00:03:49.729Z",
    "urls_found": 0,
    "status": "exhausted",
    "exhausted": true,
    "tier_reached": 5,
    "tiers_run": [
      1,
      2,
      3,
      4,
      5
    ],
    "method": "jina_reader+fxtwitter_public+tiered",
    "date_range": {
      "from": "2026-03-31",
      "to": "2026-07-06"
    }
  },
  "stanceMatrix": {
    "policySlug": "komei-kokumin",
    "dataPath": "data/policy-matrix/komei-kokumin.json",
    "disclaimer": "出典付きの事実整理です（メリデメベース）。"
  },
  "arcSummary": [
    {
      "date": "2026-05-29",
      "text": "学校教育法 デジタル教科書 改正：語学の音声、実験手順の動画など、紙だけでは伝えにくい内容を正式な教科書の一部として扱いやすくなる。"
    },
    {
      "date": "2026-05-29",
      "text": "学校教育法 デジタル教科書 改正：文部科学省は紙を一律廃止しないと説明しているが、どの教科・学年でどう使い分けるかは今後の指針と採択運用に左右される。"
    },
    {
      "date": "2026-06-10",
      "text": "正規のデジタル教科書や紙・デジタル併用型も、義務教育段階で無償給与の対象になる。"
    },
    {
      "date": "2026-06-10",
      "text": "学校教育法 デジタル教科書 改正：附帯決議は、教科書分量やデジタル教材との役割分担を検討し、子どもと学校現場の負担軽減を図るよう求めている。"
    }
  ],
  "timeline": [
    {
      "id": "komei-kokumin-fact-0",
      "type": "source",
      "date": "2026-06-10",
      "summaryPlain": "正規のデジタル教科書や紙・デジタル併用型も、義務教育段階で無償給与の対象になる。",
      "sourceUrl": "https://www.kyobun.co.jp/article/2026061002"
    },
    {
      "id": "komei-kokumin-fact-1",
      "type": "source",
      "date": "2026-06-10",
      "summaryPlain": "附帯決議は、教科書分量やデジタル教材との役割分担を検討し、子どもと学校現場の負担軽減を図るよう求めている。",
      "sourceUrl": "https://www.kyobun.co.jp/article/2026061002"
    },
    {
      "id": "komei-kokumin-fact-2",
      "type": "source",
      "date": "2026-05-29",
      "summaryPlain": "語学の音声、実験手順の動画など、紙だけでは伝えにくい内容を正式な教科書の一部として扱いやすくなる。",
      "sourceUrl": "https://www.mext.go.jp/b_menu/activity/detail/2026/20260529_2.html"
    },
    {
      "id": "komei-kokumin-fact-3",
      "type": "source",
      "date": "2026-05-29",
      "summaryPlain": "文部科学省は紙を一律廃止しないと説明しているが、どの教科・学年でどう使い分けるかは今後の指針と採択運用に左右される。",
      "sourceUrl": "https://www.mext.go.jp/b_menu/activity/detail/2026/20260529_2.html"
    }
  ],
  "qaReview": {
    "status": "ok",
    "agent": "site-debugger",
    "checkedAt": "2026-06-29T06:31:18.833Z",
    "note": "本番確認済（https://seiji1192.site/case/komei-kokumin/）HTTP 200"
  },
  "pageReady": true,
  "enrichedAt": "2026-07-06T00:03:52.036Z",
  "prosCons": {
    "disclaimer": "公表・統計等の出典に基づく整理です。政治的主張の真偽はここでは断定しません。",
    "merits": [
      {
        "headline": "動画・音声も教科書に入れられる",
        "text": "語学の音声、実験手順の動画など、紙だけでは伝えにくい内容を正式な教科書の一部として扱いやすくなる。",
        "figure": "検定・採択対象",
        "sourceUrl": "https://www.mext.go.jp/b_menu/activity/detail/2026/20260529_2.html",
        "sourceLabel": "文部科学省",
        "sourceDate": "2026-05-29"
      },
      {
        "headline": "義務教育の無償配布対象に入る",
        "text": "正規のデジタル教科書や紙・デジタル併用型も、義務教育段階で無償給与の対象になる。",
        "figure": "2027年4月施行予定",
        "sourceUrl": "https://www.kyobun.co.jp/article/2026061002",
        "sourceLabel": "教育新聞",
        "sourceDate": "2026-06-10"
      }
    ],
    "demerits": [
      {
        "headline": "現場負担が増える懸念",
        "text": "附帯決議は、教科書分量やデジタル教材との役割分担を検討し、子どもと学校現場の負担軽減を図るよう求めている。",
        "figure": "附帯決議",
        "sourceUrl": "https://www.kyobun.co.jp/article/2026061002",
        "sourceLabel": "教育新聞",
        "sourceDate": "2026-06-10"
      },
      {
        "headline": "紙とデジタルの使い分けが未確定",
        "text": "文部科学省は紙を一律廃止しないと説明しているが、どの教科・学年でどう使い分けるかは今後の指針と採択運用に左右される。",
        "figure": "2030年度以降順次導入見通し",
        "sourceUrl": "https://www.mext.go.jp/b_menu/activity/detail/2026/20260529_2.html",
        "sourceLabel": "文部科学省",
        "sourceDate": "2026-05-29"
      }
    ],
    "methodologyVersion": "v2-writer"
  },
  "xPostsPolicy": "unavailable",
  "caseType": "policy_debate",
  "contentBlocks": true,
  "adminHidden": false,
  "publishedAt": "2026-07-05T05:10:47.621Z",
  "publishedBy": "owner",
  "summaryFixedAt": "2026-07-07T01:48:27.977Z",
  "editorialRulesAppliedAt": "2026-07-22T16:09:34.468Z"
}
